procrastination_helper/__init__.py
procrastination_helper/__main__.py
procrastination_helper/customexcuses.py
procrastination_helper/delay_timer.py
procrastination_helper/get_excuse.py
procrastination_helper/list_of_excuses.py
procrastination_helper/quotes.py
procrastination_helper/data/__init__.py
procrastination_helper/data/excusesData.py
procrastination_helper/data/quotesData.py
procrastination_helper-0.1.2.dist-info/licenses/LICENSE
procrastination_helper-0.1.2.dist-info/METADATA
procrastination_helper-0.1.2.dist-info/WHEEL
procrastination_helper-0.1.2.dist-info/entry_points.txt
procrastination_helper-0.1.2.dist-info/top_level.txt
procrastination_helper-0.1.2.dist-info/RECORD
