Metadata-Version: 2.4
Name: procrastination_helper
Version: 0.1.2
Summary: A fun package to help procrastinators with excuses, quotes, and more
Author-email: Chris Leu <cl3880@nyu.edu>, Ava August <aca9900@nyu.edu>, Keith Dusling <ksd332@nyu.edu>, Joel Kim <jdk9137@nyu.edu>
License:                     GNU GENERAL PUBLIC LICENSE
Project-URL: Homepage, https://github.com/software-students-spring2025/3-python-package-market-correction
Project-URL: Repository, https://github.com/software-students-spring2025/3-python-package-market-correction.git
Project-URL: Bug Tracker, https://github.com/software-students-spring2025/3-python-package-market-correction/issues
Keywords: procrastination,excuses,quotes,python,package,build,tutorial
Classifier: Programming Language :: Python :: 3
Classifier: Intended Audience :: Education
Classifier: License :: OSI Approved :: GNU General Public License v3 (GPLv3)
Classifier: Operating System :: OS Independent
Requires-Python: >=3.7
License-File: LICENSE
Provides-Extra: dev
Requires-Dist: pytest; extra == "dev"
Dynamic: license-file
